src/__init__.py
src/__main__.py
src/capabilities/__init__.py
src/capabilities/code_lens.py
src/capabilities/completions.py
src/capabilities/definitions.py
src/capabilities/find_references.py
src/capabilities/hover.py
src/capabilities/lint.py
src/commands/__init__.py
src/commands/dotexport.py
src/commands/outline.py
src/generators/__init__.py
src/generators/vscode/__init__.py
src/generators/vscode/coloring.py
src/generators/vscode/vscode_generator.py
src/infrastructure/__init__.py
src/infrastructure/configuration.py
src/infrastructure/language_server.py
src/infrastructure/lsp.py
src/infrastructure/server.py
src/infrastructure/textx_ls.py
src/infrastructure/workspace.py
src/metamodel/__init__.py
src/metamodel/coloring.tx
src/metamodel/completions.tx
src/metamodel/configuration.tx
src/metamodel/outline.tx
src/metamodel/textx.tx
src/utils/__init__.py
src/utils/_utils.py
src/utils/constants.py
src/utils/uris.py
textXls-1.1.0.dist-info/METADATA
textXls-1.1.0.dist-info/RECORD
textXls-1.1.0.dist-info/WHEEL
textXls-1.1.0.dist-info/dependency_links.txt
textXls-1.1.0.dist-info/entry_points.txt
textXls-1.1.0.dist-info/top_level.txt
third_party/__init__.py
third_party/arpeggio/__init__.py
third_party/arpeggio/cleanpeg.py
third_party/arpeggio/export.py
third_party/arpeggio/peg.py
third_party/arpeggio/utils.py
third_party/funcsigs/__init__.py
third_party/funcsigs/version.py
third_party/jinja2/__init__.py
third_party/jinja2/_compat.py
third_party/jinja2/_stringdefs.py
third_party/jinja2/asyncfilters.py
third_party/jinja2/asyncsupport.py
third_party/jinja2/bccache.py
third_party/jinja2/compiler.py
third_party/jinja2/constants.py
third_party/jinja2/debug.py
third_party/jinja2/defaults.py
third_party/jinja2/environment.py
third_party/jinja2/exceptions.py
third_party/jinja2/ext.py
third_party/jinja2/filters.py
third_party/jinja2/idtracking.py
third_party/jinja2/lexer.py
third_party/jinja2/loaders.py
third_party/jinja2/meta.py
third_party/jinja2/nodes.py
third_party/jinja2/optimizer.py
third_party/jinja2/parser.py
third_party/jinja2/runtime.py
third_party/jinja2/sandbox.py
third_party/jinja2/tests.py
third_party/jinja2/utils.py
